nhsmm/__init__.py
nhsmm/__version__.py
nhsmm/config.py
nhsmm/context.py
nhsmm/convergence.py
nhsmm/data.py
nhsmm/encoder.py
nhsmm/distributions/__init__.py
nhsmm/distributions/default.py
nhsmm/models/__init__.py
nhsmm/models/base.py
nhsmm-0.0.4a0.dist-info/licenses/LICENSE
nhsmm-0.0.4a0.dist-info/METADATA
nhsmm-0.0.4a0.dist-info/WHEEL
nhsmm-0.0.4a0.dist-info/top_level.txt
nhsmm-0.0.4a0.dist-info/RECORD
