Metadata-Version: 2.4
Name: nhsmm
Version: 0.0.4a0
Summary: Neural Hidden Semi-Markov Model (NHSMM) implementation in PyTorch
Author-email: AWA <dev@awa.si>
License:                                  Apache License
Project-URL: Homepage, https://github.com/awa-si/NHSMM
Project-URL: Repository, https://github.com/awa-si/NHSMM
Project-URL: Issues, https://github.com/awa-si/NHSMM/issues
Project-URL: Documentation, https://github.com/awa-si/NHSMM/wiki
Keywords: hsmm,hidden semi-markov model,neural hsmm,pytorch,sequence modeling,temporal modeling,regime detection
Classifier: Development Status :: 4 - Beta
Classifier: Intended Audience :: Science/Research
Classifier: Intended Audience :: Developers
Classifier: License :: OSI Approved :: Apache Software License
Classifier: Programming Language :: Python
Classifier: Programming Language :: Python :: 3
Classifier: Programming Language :: Python :: 3.9
Classifier: Programming Language :: Python :: 3.10
Classifier: Programming Language :: Python :: 3.11
Classifier: Programming Language :: Python :: 3.12
Classifier: Programming Language :: Python :: 3.13
Classifier: Operating System :: OS Independent
Classifier: Topic :: Scientific/Engineering
Classifier: Topic :: Scientific/Engineering :: Artificial Intelligence
Classifier: Topic :: Scientific/Engineering :: Information Analysis
Requires-Python: >=3.9
License-File: LICENSE
Requires-Dist: torch>=2.2
Requires-Dist: numpy>=1.26
Requires-Dist: scipy>=1.11
Requires-Dist: scikit-learn>=1.4
Requires-Dist: typing_extensions>=4.12
Provides-Extra: viz
Requires-Dist: matplotlib>=3.9; extra == "viz"
Provides-Extra: opt
Requires-Dist: optuna>=3.6; extra == "opt"
Provides-Extra: data
Requires-Dist: polars>=1.36; extra == "data"
Provides-Extra: dev
Requires-Dist: pytest>=8.2; extra == "dev"
Requires-Dist: pytest-cov>=5.0; extra == "dev"
Requires-Dist: ruff>=0.6; extra == "dev"
Requires-Dist: black>=24.4; extra == "dev"
Requires-Dist: mypy>=1.11; extra == "dev"
Requires-Dist: pre-commit>=3.7; extra == "dev"
Requires-Dist: build>=1.2; extra == "dev"
Requires-Dist: twine>=5.1; extra == "dev"
Dynamic: license-file
